{
    "id": "cupertino.Shortcuts.1",
    "element": "Shortcuts",
    "sourcePath": "lib/src/widgets/shortcuts.dart",
    "sourceLine": 920,
    "channel": "stable",
    "serial": "1",
    "package": "flutter",
    "library": "cupertino",
    "copyright": null,
    "description": "Here, we will use the [Shortcuts] and [Actions] widgets to add and subtract\nfrom a counter. When the child widget has keyboard focus, and a user presses\nthe keys that have been defined in [Shortcuts], the action that is bound\nto the appropriate [Intent] for the key is invoked.\n\nIt also shows the use of a [CallbackAction] to avoid creating a new [Action]\nsubclass.",
    "file": "cupertino.Shortcuts.1.dart"
}