{
    "id": "material.FloatingActionButton.4",
    "element": "FloatingActionButton",
    "sourcePath": "lib/src/material/floating_action_button.dart",
    "sourceLine": 95,
    "channel": "stable",
    "serial": "4",
    "package": "flutter",
    "library": "material",
    "copyright": null,
    "description": "This sample shows the creation of all the variants of [FloatingActionButton] widget as\ndescribed in: https://m3.material.io/components/floating-action-button/overview",
    "file": "material.FloatingActionButton.4.dart"
}